sklearn_llm/__init__.py
sklearn_llm/base.py
sklearn_llm/example.py
sklearn_llm/llms.py
sklearn_llm/transformation.py
sklearn_llm-0.1.1.dist-info/LICENSE
sklearn_llm-0.1.1.dist-info/METADATA
sklearn_llm-0.1.1.dist-info/WHEEL
sklearn_llm-0.1.1.dist-info/RECORD
