Metadata-Version: 2.3
Name: sklearn-llm
Version: 0.1.1
Summary: A tiny module for combining LLM transformations with scikit-learn
License: MIT
Author: Trung Nguyen
Author-email: trung.ngvan@gmail.com
Requires-Python: >=3.10,<4.0
Classifier: License :: OSI Approved :: MIT License
Classifier: Programming Language :: Python :: 3
Classifier: Programming Language :: Python :: 3.10
Classifier: Programming Language :: Python :: 3.11
Classifier: Programming Language :: Python :: 3.12
Classifier: Programming Language :: Python :: 3.13
Requires-Dist: aiohttp (==3.11.10)
Requires-Dist: asyncio (>=3.4.3,<4.0.0)
Requires-Dist: jinja2 (>=3.1.5,<4.0.0)
Requires-Dist: openai (>=1.65.0,<2.0.0)
Requires-Dist: python-dotenv (>=1.0.1,<2.0.0)
Requires-Dist: scikit-learn (>=1.5.0,<2.0.0)
